nineml/__init__.py
nineml/annotations.py
nineml/base.py
nineml/document.py
nineml/exceptions.py
nineml/reference.py
nineml/sugar.py
nineml/units.py
nineml/values.py
nineml/version.py
nineml/abstraction/__init__.py
nineml/abstraction/base.py
nineml/abstraction/ports.py
nineml/abstraction/componentclass/__init__.py
nineml/abstraction/componentclass/base.py
nineml/abstraction/componentclass/visitors/__init__.py
nineml/abstraction/componentclass/visitors/modifiers.py
nineml/abstraction/componentclass/visitors/queriers.py
nineml/abstraction/componentclass/visitors/validators/__init__.py
nineml/abstraction/componentclass/visitors/validators/general.py
nineml/abstraction/componentclass/visitors/validators/names.py
nineml/abstraction/componentclass/visitors/validators/types.py
nineml/abstraction/connectionrule/__init__.py
nineml/abstraction/connectionrule/base.py
nineml/abstraction/connectionrule/visitors/__init__.py
nineml/abstraction/connectionrule/visitors/base.py
nineml/abstraction/connectionrule/visitors/modifiers.py
nineml/abstraction/connectionrule/visitors/queriers.py
nineml/abstraction/connectionrule/visitors/validators/__init__.py
nineml/abstraction/connectionrule/visitors/validators/base.py
nineml/abstraction/connectionrule/visitors/validators/general.py
nineml/abstraction/connectionrule/visitors/validators/names.py
nineml/abstraction/connectionrule/visitors/validators/types.py
nineml/abstraction/dynamics/__init__.py
nineml/abstraction/dynamics/base.py
nineml/abstraction/dynamics/regimes.py
nineml/abstraction/dynamics/transitions.py
nineml/abstraction/dynamics/visitors/__init__.py
nineml/abstraction/dynamics/visitors/base.py
nineml/abstraction/dynamics/visitors/modifiers.py
nineml/abstraction/dynamics/visitors/queriers.py
nineml/abstraction/dynamics/visitors/validators/__init__.py
nineml/abstraction/dynamics/visitors/validators/base.py
nineml/abstraction/dynamics/visitors/validators/general.py
nineml-1.0.1.dist-info/METADATA
nineml-1.0.1.dist-info/RECORD
nineml-1.0.1.dist-info/WHEEL
nineml-1.0.1.dist-info/top_level.txt
