Metadata-Version: 2.1
Name: nineml
Version: 1.0.1
Summary: A tool for reading, writing and generally working with 9ML objects and files.
Home-page: http://nineml-python.readthedocs.io
Author: Andrew P. Davison, Thomas G. Close, Mike Hull, Eilif Muller
Author-email: tom.g.close@gmail.com
License: BSD 3 License
Keywords: computational neuroscience modeling interoperability XML YAMLHDF5 JSON
Platform: UNKNOWN
Classifier: Development Status :: 5 - Production/Stable
Classifier: Environment :: Console
Classifier: Intended Audience :: Science/Research
Classifier: License :: OSI Approved :: BSD License
Classifier: Natural Language :: English
Classifier: Operating System :: OS Independent
Classifier: Programming Language :: Python :: 2
Classifier: Programming Language :: Python :: 2.7
Classifier: Programming Language :: Python :: 3
Classifier: Programming Language :: Python :: 3.4
Classifier: Programming Language :: Python :: 3.5
Classifier: Programming Language :: Python :: 3.6
Classifier: Topic :: Scientific/Engineering
Requires-Python: >=2.7, !=3.0.*, !=3.1.*, !=3.2.*, <4
Requires-Dist: lxml (>=3.7.3)
Requires-Dist: future (>=0.16.0)
Requires-Dist: h5py (>=2.7.0)
Requires-Dist: PyYAML (>=3.1)
Requires-Dist: sympy (>=1.2)
